{
  "type": "CTA",
  "study_id": "VTX-330-201",
  "site_id": "ARP-12",
  "investigator": "VANTIX BIOSCIENCES",
  "sponsor": "VANTIX BIOSCIENCES",
  "holdback_percent": 0.0,
  "overhead_percent": 0.0,
  "budget": [
    {
      "visit_name": "Screening",
      "procedures": [],
      "amount": 685.4
    },
    {
      "visit_name": "Vi",
      "procedures": [],
      "amount": 418.75
    },
    {
      "visit_name": "V2",
      "procedures": [],
      "amount": 842.6
    },
    {
      "visit_name": "V3",
      "procedures": [],
      "amount": 523.1
    },
    {
      "visit_name": "v4",
      "procedures": [],
      "amount": 471.5
    }
  ],
  "site_fees": [
    {
      "name": "Site Initiation / Start-up",
      "amount": 8000.0,
      "cap": null
    },
    {
      "name": "IRB / Regulatory Submission",
      "amount": 3500.0,
      "cap": null
    }
  ],
  "_source_file": "CTA_VTX-330-201.pdf"
}