{
  "type": "CTA",
  "study_id": "MRD-204-017",
  "site_id": "ARP-12",
  "investigator": "Elena Park",
  "sponsor": "Meridian Therapeutics, Inc.",
  "holdback_percent": 10.0,
  "overhead_percent": 25.0,
  "budget": [
    {
      "visit_name": "Screening+TVU",
      "procedures": [],
      "amount": 2387.0
    },
    {
      "visit_name": "Screening",
      "procedures": [],
      "amount": 1722.5
    },
    {
      "visit_name": "DXA",
      "procedures": [],
      "amount": 1099.0
    },
    {
      "visit_name": "TVU",
      "procedures": [],
      "amount": 664.5
    },
    {
      "visit_name": "Imaging",
      "procedures": [],
      "amount": 1868.5
    },
    {
      "visit_name": "UnschLab",
      "procedures": [],
      "amount": 371.0
    },
    {
      "visit_name": "UnschVisit",
      "procedures": [],
      "amount": 605.0
    }
  ],
  "site_fees": [
    {
      "name": "Site Start-up",
      "amount": 2983.75,
      "cap": null
    },
    {
      "name": "Administrative Fee",
      "amount": 2153.13,
      "cap": null
    },
    {
      "name": "Pharmacy Annual Maintenance",
      "amount": 1373.75,
      "cap": null
    },
    {
      "name": "Advertising / Patient Recruitment",
      "amount": 830.63,
      "cap": null
    },
    {
      "name": "Pre-screen Chart Review",
      "amount": 2335.63,
      "cap": 3000.0
    }
  ],
  "_source_file": "CTA_MRD-204-017.pdf"
}